{
    "Type": "Node",
    "Id": "LeLouvre",
    "Steps": [
        {
            "Type": "Text",
            "Vibration": "true",
            "Label": {
                "en": "I'm sure you've heard of the Louvre museum",
                "fr": "Je suis sûr que tu as entendu parler du Musée du Louvre",
                "es": "I'm sure you've heard of the Louvre museum",
                "zh": "I'm sure you've heard of the Louvre museum"
            }
        },
        {
            "Type": "Image",
            "Parameters": {
                "Display": "FullScreenWidth",
                "Width": 460,
                "Height": 397,
                "Source": "Internal",
                "Path": "/museums/paris/thumbnails/louvre_thumbnail.jpg"
            }
        },
        {
            "Type": "Text",
            "Label": {
                "en": "The largest museum in the world... 10 million visitors in 2019",
                "fr": "Le plus grand musée du monde... 10 millions de visiteurs en 2019",
                "es": "The largest museum in the world... 10 million visitors in 2019",
                "zh": "The largest museum in the world... 10 million visitors in 2019"
            }
        },
        {
            "Type": "Text",
            "Label": {
                "en": "But did you know that it used to be a castle?",
                "fr": "Savais-tu qu'à l'origine c'était un château  ?",
                "es": "But did you know that it used to be a castle?",
                "zh": "But did you know that it used to be a castle?"
            }
        }
    ],
    "Commands": [
        {
            "Type": "Node",
            "Id": "LeLouvreNo",
            "ElementValue": "1",
            "CommandLabel": {
                "en": "No",
                "fr": "Non",
                "es": "No",
                "zh": "No"
            },
            "Steps": [
                {
                    "Type": "Text",
                    "Label": {
                        "en": "It was! Hundreds of years ago",
                        "fr": "C'était pourtant sa vocation première",
                        "es": "It was! Hundreds of years ago",
                        "zh": "It was! Hundreds of years ago"
                    }
                }
            ],
            "LinksToFragment": {
                "FragmentPath": "LeLouvre2"
            }
        },
        {
            "Type": "Node",
            "Id": "LeLouvreYes",
            "ElementValue": "1",
            "CommandLabel": {
                "en": "Yes",
                "fr": "Oui",
                "es": "Yes",
                "zh": "Yes"
            },
            "Steps": [
                {
                    "Type": "Text",
                    "Label": {
                        "en": "It was! Hundreds of years ago!",
                        "fr": "C'était bien le cas ! Il y a plusieurs centaines d'années !",
                        "es": "It was! Hundreds of years ago!",
                        "zh": "It was! Hundreds of years ago!"
                    }
                }
            ],
            "LinksToFragment": {
                "FragmentPath": "LeLouvre2"
            }
        }
    ]
}
